new_project_floris/__init__.py
new_project_floris/add.py
new_project_floris-0.1.0.dist-info/METADATA
new_project_floris-0.1.0.dist-info/WHEEL
new_project_floris-0.1.0.dist-info/entry_points.txt
new_project_floris-0.1.0.dist-info/RECORD
