Metadata-Version: 2.4
Name: new-project-floris
Version: 0.1.0
Summary: Add your description here
Author-email: Floris vanderFlier <floris.vanderflier@iff.com>
Requires-Python: >=3.12
Requires-Dist: pytest>=8.3.5
Requires-Dist: ruff>=0.11.2
